{
  "generatedAt": "2026-06-15T16:10:00-04:00",
  "week": "W9",
  "phase": "Base",
  "summary": "Base W9 — first post-deload week, shallow step-up greenlit by Sun 6/14 both-clean AM (Adj #89 resolves Adj #87). §4.C prescribes 35 min Mon / 4×8 min @ T Tue / 30 min Thu / 40 min + 6 strides Fri / 60 min long Sat + Hyp B PM; v4.3 cap ~20 mpw. RELEASED: hill-stride debut (Adj #44 — Mon), calf 335 bump (Adj #40 — Sat). T target nudged to ~7:50–7:55/mi (Adj #77) for Tue's 4×8. Bumps queued: preacher 65 (Adj #83); holds-until-clean: lat 155 (Adj #80), pushdown 22.5/arm pain-gated (Adj #84). Knee watch — went bilateral DURING Sat's run; §11.D bar holds Phase C opt-ins parked. Lift schedule unchanged. Tennis elbow clock reset W8 Tue (Adj #75) — keep §10.A dailies.",
  "days": [
    { "date": "2026-06-15", "day": "Mon", "session": "Z1 easy 35 min + hill strides 6×10–12s @ 4–6%", "note": "Hill-stride debut RELEASED (Adj #44/#89); if already ran flat, debut lands W10 Mon. Vomero on easy; cadence cap ≤180", "status": "today" },
    { "date": "2026-06-16", "day": "Tue", "session": "Threshold 4×8 min @ T (90s rec)", "note": "T target nudged 7:50–7:55/mi per Adj #77; anchor RPE ≤7, fall back to 8:00 if RPE 8+", "status": "upcoming" },
    { "date": "2026-06-17", "day": "Wed", "session": "Hyp A (standalone, no run)", "note": "Incline 145 repeat (miss #1, Adj #47/#71); DB lat hold 30 (Adj #72); preacher BUMP 65 (Adj #83); pushdown 22.5/arm hold (Adj #84); rear-delt fly 125; decline crunch BW", "status": "upcoming" },
    { "date": "2026-06-18", "day": "Thu", "session": "Z1 easy 30 min", "note": "Recovery aerobic; revert to rest on yellow/red AM (§11.C)", "status": "upcoming" },
    { "date": "2026-06-19", "day": "Fri", "session": "Z1 easy 40 min + 6×20s strides", "note": "§4.C W9 Fri (not VO2max yet — VO2max starts W13). Cadence ≤180 on strides", "status": "upcoming" },
    { "date": "2026-06-20", "day": "Sat", "session": "Long Z1 60 min AM + Hyp B PM (≥6h gap)", "note": "Lat 155 hold (Adj #80); chest-supp row revert 85 (Adj #81); Sat DB lat 30 push reps (Adj #82); preacher 65 if Wed clean; pushdown 22.5/arm hold; calf 325 (335 held — Adj #40/#87); chest fly 130 (Adj #88); decline crunch BW", "status": "upcoming" },
    { "date": "2026-06-21", "day": "Sun", "session": "Off / SI prehab", "note": "Tyler 3×15 + reverse Tyler 3×15, McGill Big 3 5-3-1, clamshell + bird-dog", "status": "upcoming" }
  ]
}
